seppy/__init__.py
seppy/_version.py
seppy/version.py
seppy/data/bepi_sixsp_instrumental_constants/sixsp_side0_e_combined_gf.csv
seppy/data/bepi_sixsp_instrumental_constants/sixsp_side0_e_gf_en.csv
seppy/data/bepi_sixsp_instrumental_constants/sixsp_side0_p_combined_gf.csv
seppy/data/bepi_sixsp_instrumental_constants/sixsp_side0_p_gf_en.csv
seppy/data/bepi_sixsp_instrumental_constants/sixsp_side0_pe_gf_en.csv
seppy/data/bepi_sixsp_instrumental_constants/sixsp_side1_e_combined_gf.csv
seppy/data/bepi_sixsp_instrumental_constants/sixsp_side1_e_gf_en.csv
seppy/data/bepi_sixsp_instrumental_constants/sixsp_side1_p_combined_gf.csv
seppy/data/bepi_sixsp_instrumental_constants/sixsp_side1_p_gf_en.csv
seppy/data/bepi_sixsp_instrumental_constants/sixsp_side1_pe_gf_en.csv
seppy/data/bepi_sixsp_instrumental_constants/sixsp_side2_e_combined_gf.csv
seppy/data/bepi_sixsp_instrumental_constants/sixsp_side2_e_gf_en.csv
seppy/data/bepi_sixsp_instrumental_constants/sixsp_side2_p_combined_gf.csv
seppy/data/bepi_sixsp_instrumental_constants/sixsp_side2_p_gf_en.csv
seppy/data/bepi_sixsp_instrumental_constants/sixsp_side2_pe_gf_en.csv
seppy/data/bepi_sixsp_instrumental_constants/sixsp_side3_e_combined_gf.csv
seppy/data/bepi_sixsp_instrumental_constants/sixsp_side3_e_gf_en.csv
seppy/data/bepi_sixsp_instrumental_constants/sixsp_side3_p_combined_gf.csv
seppy/data/bepi_sixsp_instrumental_constants/sixsp_side3_p_gf_en.csv
seppy/data/bepi_sixsp_instrumental_constants/sixsp_side3_pe_gf_en.csv
seppy/data/bepi_sixsp_instrumental_constants/sixsp_side4_e_combined_gf.csv
seppy/data/bepi_sixsp_instrumental_constants/sixsp_side4_e_gf_en.csv
seppy/data/bepi_sixsp_instrumental_constants/sixsp_side4_p_combined_gf.csv
seppy/data/bepi_sixsp_instrumental_constants/sixsp_side4_p_gf_en.csv
seppy/data/bepi_sixsp_instrumental_constants/sixsp_side4_pe_gf_en.csv
seppy/data/test/20230719_side0.csv
seppy/data/test/20230719_side1.csv
seppy/data/test/20230719_side2.csv
seppy/data/test/epi21106.rl2
seppy-0.4.3.dist-info/licenses/LICENSE.rst
seppy-0.4.3.dist-info/METADATA
seppy-0.4.3.dist-info/WHEEL
seppy-0.4.3.dist-info/top_level.txt
seppy-0.4.3.dist-info/RECORD
