Metadata-Version: 2.4
Name: seppy
Version: 0.4.3
Summary: SEPpy
Author-email: Jan Gieseler <jan.gieseler@utu.fi>
License-Expression: BSD-3-Clause
Project-URL: repository, https://github.com/serpentine-h2020/SEPpy
Classifier: Intended Audience :: Science/Research
Classifier: Natural Language :: English
Classifier: Operating System :: OS Independent
Classifier: Programming Language :: Python
Classifier: Programming Language :: Python :: 3.9
Classifier: Programming Language :: Python :: 3.10
Classifier: Programming Language :: Python :: 3.11
Classifier: Programming Language :: Python :: 3.12
Classifier: Programming Language :: Python :: 3.13
Classifier: Programming Language :: Python :: 3.14
Classifier: Topic :: Scientific/Engineering :: Physics
Requires-Python: >=3.9
License-File: LICENSE.rst
Requires-Dist: astropy
Requires-Dist: astroquery
Requires-Dist: bs4
Requires-Dist: cdflib
Requires-Dist: ipympl
Requires-Dist: ipywidgets
Requires-Dist: matplotlib
Requires-Dist: mpl-animators>=1.0.0
Requires-Dist: numpy
Requires-Dist: pandas
Requires-Dist: pooch
Requires-Dist: psutil
Requires-Dist: requests
Requires-Dist: solo-epd-loader
Requires-Dist: sunpy[all]>=4.1.0
Requires-Dist: tqdm
Provides-Extra: test
Requires-Dist: pytest; extra == "test"
Requires-Dist: pytest-doctestplus; extra == "test"
Requires-Dist: pytest-cov; extra == "test"
Provides-Extra: docs
Requires-Dist: sphinx; extra == "docs"
Requires-Dist: sphinx-automodapi; extra == "docs"
Dynamic: license-file
